setup.py
Unifiber/__init__.py
Unifiber/dist_cables_labelling.py
Unifiber/feeder_cables_labelling.py
Unifiber/imp_Geostruct.py
Unifiber/limpar_export.py
Unifiber/tools.py
Unifiber.egg-info/PKG-INFO
Unifiber.egg-info/SOURCES.txt
Unifiber.egg-info/dependency_links.txt
Unifiber.egg-info/not-zip-safe
Unifiber.egg-info/top_level.txt