Metadata-Version: 2.1
Name: Unifiber
Version: 0.1
Summary: teste new qgis modules
Author-email: joaquim.cardoso@byonsolutions.com
